Workbook

Sheet Sheet1
A1: 名称 1 | B1: 供应商 | C1: 国 | D1: 名称 1 | E1: 城市 | F1: 地区 | G1: 地址 | H1: 街道 | I1: 组 | J1: 语言 | K1: 电话1 | L1: 税号 5 | M1: 标题 | N1: 公司 | O1: 日期 | P1: 创建者 | Q1: AGrp | R1: Tr.prt | S1: 标题
A2: 北京西飞世纪门窗幕墙工程有限责任公司 | B2: 4000002942 | C2: CN | D2: 北京西飞世纪门窗幕墙工程有限责任公司 | E2: 北京 | F2: 北京 | G2: 106658 | H2: 北京 | I2: Z004 | J2: ZH | L2: 999 | N2: 9776 | O2: 42735 | P2: FI01 | S2: 公司
A3: 北京燕侨物业管理有限公司 | B3: 2000001624 | C3: CN | D3: 北京燕侨物业管理有限公司 | F3: 北京市 | G3: 106597 | H3: 北京市朝阳区建国门外大街24号 | I3: Z002 | J3: ZH | K3: 010-65150326 | L3: 91110105600004996U | N3: 9776 | O3: 42735 | P3: FI01 | S3: 公司
A4: 戴勇 | B4: 2000001625 | C4: CN | D4: 戴勇 | E4: 上海市 | F4: 上海市 | G4: 106598 | H4: 上海浦东新区云台路 | I4: Z002 | J4: ZH | K4: 18113652781 | L4: 310107198701200317 | N4: 9776 | O4: 42735 | P4: FI01 | S4: 先生
A5: 工商银行上海市浦东分行 | B5: 3000000465 | C5: CN | D5: 工商银行上海市浦东分行 | E5: 上海市 | F5: 上海市 | G5: 106599 | H5: 上海市浦东新区浦东南路2024号 | I5: Z003 | J5: ZH | K5: 021-58759075 | L5: 999 | N5: 9776 | O5: 42735 | P5: FI01 | S5: 公司
A6: 金叶俊 | B6: 2000001627 | C6: CN | D6: 金叶俊 | F6: 上海市 | G6: 106601 | H6: 上海普陀区长寿路 | I6: Z002 | J6: ZH | K6: 15801652813 | L6: 999 | N6: 9776 | O6: 42735 | P6: FI01 | S6: 先生
A7: 润森环境服务（上海）有限公司 | B7: 2000001628 | C7: CN | D7: 润森环境服务（上海）有限公司 | E7: 上海市 | F7: 上海市 | G7: 106602 | H7: 上海市普陀区长寿路1076号飞雕商务大厦1902室 | I7: Z002 | J7: ZH | K7: 13585655788 | L7: 91310114078158967C | N7: 9776 | O7: 42735 | P7: FI01 | S7: 公司
A8: 上海安保设备开发工程有限公司 | B8: 1000004348 | C8: CN | D8: 上海安保设备开发工程有限公司 | E8: 上海市 | F8: 上海市 | G8: 106603 | H8: 上海市浦东新区高青路3368号4楼 | I8: Z001 | J8: ZH | K8: 13301602716 | L8: 91310109132202544H | N8: 9776 | O8: 42735 | P8: FI01 | S8: 公司
A9: 上海博世机电设施工程有限公司 | B9: 1000004349 | C9: CN | D9: 上海博世机电设施工程有限公司 | E9: 上海市 | F9: 上海市 | G9: 106604 | H9: 上海浦东大道2515号金茂花园南楼903室 | I9: Z001 | J9: ZH | K9: 13501801873 | L9: 91310112785876001M | N9: 9776 | O9: 42735 | P9: FI01 | S9: 公司
A10: 上海不唯间贸易有限公司 | B10: 2000001629 | C10: CN | D10: 上海不唯间贸易有限公司 | F10: 上海市 | G10: 106605 | H10: 上海嘉定嘉定区安亭镇园区路1168号4幢2736室 | I10: Z002 | J10: ZH | K10: 021-59575884 | L10: 999 | N10: 9776 | O10: 42735 | P10: FI01 | S10: 公司
A11: 上海步景标识有限公司 | B11: 1000004350 | C11: CN | D11: 上海步景标识有限公司 | E11: 上海市 | F11: 上海市 | G11: 106606 | H11: 上海市宝山区沪太路6289弄20号 | I11: Z001 | J11: ZH | K11: 15900793386 | L11: 999 | N11: 9776 | O11: 42735 | P11: FI01 | S11: 公司
A12: 上海春婕花木园艺有限公司 | B12: 2000001631 | C12: CN | D12: 上海春婕花木园艺有限公司 | E12: 上海市 | F12: 上海市 | G12: 106608 | H12: 上海市宝山区漠河路600弄东鼎国际B座903室 | I12: Z002 | J12: ZH | K12: 13122814969 | L12: 913101147639842988 | N12: 9776 | O12: 42735 | P12: FI01 | S12: 公司
A13: 上海大庭信息技术有限公司 | B13: 2000001632 | C13: CN | D13: 上海大庭信息技术有限公司 | E13: 上海市 | F13: 上海市 | G13: 106609 | H13: 上海市金山区朱泾镇秀州村胜利7028号一栋110室 | I13: Z002 | J13: ZH | K13: 13916679647 | L13: 999 | N13: 9776 | O13: 42735 | P13: FI01 | S13: 公司
A14: 上海德翊工程机电设备有限公司 | B14: 1000004351 | C14: CN | D14: 上海德翊工程机电设备有限公司 | E14: 上海市 | F14: 上海市 | G14: 106610 | H14: 上海市黄浦区北京西路142弄2号边门 | I14: Z001 | J14: ZH | K14: 021-63150795 | L14: 913101157956293702 | N14: 9776 | O14: 42735 | P14: FI01 | S14: 公司
A15: 上海斗牛士牛排馆有限公司 | B15: 2000001633 | C15: CN | D15: 上海斗牛士牛排馆有限公司 | E15: 上海市 | F15: 上海市 | G15: 106611 | H15: 上海市徐汇区岳阳路1号 | I15: Z002 | J15: ZH | K15: 021-64332842 | L15: 999 | N15: 9776 | O15: 42735 | P15: FI01 | S15: 公司
A16: 上海泛远皇普信息技术股份有限公司 | B16: 3000000470 | C16: CN | D16: 上海泛远皇普信息技术股份有限公司 | F16: 上海市 | G16: 106653 | H16: 上海市黄浦区打浦路15号3803-1室 | I16: Z003 | J16: ZH | K16: 021-51532025 | L16: 91310000680978570B | N16: 9776 | O16: 42735 | P16: FI01 | S16: 公司
A17: 上海富程环保工程有限公司 | B17: 1000004352 | C17: CN | D17: 上海富程环保工程有限公司 | E17: 上海市 | F17: 上海市 | G17: 106612 | H17: 上海市万航渡路888号23F | I17: Z001 | J17: ZH | K17: 15301692053 | L17: 913102306840419299 | N17: 9776 | O17: 42735 | P17: FI01 | S17: 公司
A18: 上海高力国际物业服务有限公司 | B18: 3000000116 | C18: CN | D18: 上海高力国际物业服务有限公司 | E18: 上海 | G18: 49706 | H18: 上海浦东银城中路600弄 | I18: Z003 | J18: ZH | K18: 021-68881623 | L18: 310115400037173 | N18: 9776 | O18: 42735 | P18: FI01 | S18: 公司
A19: 上海谷泉建筑工程有限公司 | B19: 1000004353 | C19: CN | D19: 上海谷泉建筑工程有限公司 | E19: 上海市 | F19: 上海市 | G19: 106614 | H19: 上海市闸北区虬江路1150弄局东村22号 | I19: Z001 | J19: ZH | K19: 021-54935677 | L19: 999 | N19: 9776 | O19: 42735 | P19: FI01 | S19: 公司
A20: 上海海燕建筑工程有限公司 | B20: 1000004373 | C20: CN | D20: 上海海燕建筑工程有限公司 | F20: 上海市 | G20: 106654 | H20: 上海市浦东新区老港镇良欣路456号2幢452室 | I20: Z001 | J20: ZH | K20: 021-51087738 | L20: 91310115133952267G | N20: 9776 | O20: 42735 | P20: FI01 | S20: 公司
A21: 上海和瀚文化传播有限公司 | B21: 3000000466 | C21: CN | D21: 上海和瀚文化传播有限公司 | E21: 上海市 | F21: 上海市 | G21: 106615 | H21: 上海市云台路92号102室 | I21: Z003 | J21: ZH | K21: 13918309046 | L21: 913101145997659570 | N21: 9776 | O21: 42735 | P21: FI01 | S21: 公司
A22: 上海恒达广告有限公司 | B22: 3000000467 | C22: CN | D22: 上海恒达广告有限公司 | E22: 上海市 | F22: 上海市 | G22: 106616 | H22: 上海市闵行区纪翟路西花园25号 | I22: Z003 | J22: ZH | K22: 15800344088 | L22: 999 | N22: 9776 | O22: 42735 | P22: FI01 | S22: 公司
A23: 上海恒建设发展有限公司 | B23: 4000002943 | C23: CN | D23: 上海恒建设发展有限公司 | E23: 上海 | F23: 上海 | G23: 106659 | H23: 上海 | I23: Z004 | J23: ZH | L23: 999 | N23: 9776 | O23: 42735 | P23: FI01 | S23: 公司
A24: 上海恒盈建设发展有限公司 | B24: 1000004354 | C24: CN | D24: 上海恒盈建设发展有限公司 | E24: 上海市 | F24: 上海市 | G24: 106617 | H24: 上海市普陀区岚皋路597号十八英尺312室 | I24: Z001 | J24: ZH | K24: 13816076056 | L24: 91310113743758357L | N24: 9776 | O24: 42735 | P24: FI01 | S24: 公司
A25: 上海弘韬建设发展有限公司 | B25: 1000004355 | C25: CN | D25: 上海弘韬建设发展有限公司 | E25: 上海市 | F25: 上海市 | G25: 106618 | H25: 上海市黄浦区光启南路78号-2 | I25: Z001 | J25: ZH | K25: 13816405637 | L25: 999 | N25: 9776 | O25: 42735 | P25: FI01 | S25: 公司
A26: 上海宏源达防水工程有限公司 | B26: 1000004356 | C26: CN | D26: 上海宏源达防水工程有限公司 | E26: 上海市 | F26: 上海市 | G26: 106619 | H26: 上海市申滨陆1051弄100号1202室 | I26: Z001 | J26: ZH | K26: 13916892330 | L26: 999 | N26: 9776 | O26: 42735 | P26: FI01 | S26: 公司
A27: 上海环境节能工程股份有限公司 | B27: 1000004357 | C27: CN | D27: 上海环境节能工程股份有限公司 | E27: 上海市 | F27: 上海市 | G27: 106620 | H27: 上海市曲阳路158号北区4楼 | I27: Z001 | J27: ZH | K27: 021-65090068 | L27: 999 | N27: 9776 | O27: 42735 | P27: FI01 | S27: 公司
A28: 上海汇昕文化传播有限公司 | B28: 3000000468 | C28: CN | D28: 上海汇昕文化传播有限公司 | E28: 上海市 | F28: 上海市 | G28: 106621 | H28: 上海市漕宝路86号光大会展f座1904室 | I28: Z003 | J28: ZH | K28: 13611973999 | L28: 913102305852476811 | N28: 9776 | O28: 42735 | P28: FI01 | S28: 公司
A29: 上海嘉好图文设计制作有限公司 | B29: 3000000469 | C29: CN | D29: 上海嘉好图文设计制作有限公司 | F29: 上海市 | G29: 106622 | H29: 上海市嘉定区云屏路1399弄23-25号1305室 | I29: Z003 | J29: ZH | K29: 18106182318 | L29: 91310116057607882T | N29: 9776 | O29: 42735 | P29: FI01 | S29: 公司
A30: 上海静盛装饰设计有限公司 | B30: 1000004374 | C30: CN | D30: 上海静盛装饰设计有限公司 | F30: 上海市 | G30: 106655 | H30: 上海市崇明县庙镇窑桥村社南758号1幢1175室（上海庙镇经济开发区） | I30: Z001 | J30: ZH | K30: 13501685113 | L30: 91310230566524559M | N30: 9776 | O30: 42735 | P30: FI01 | S30: 公司
A31: 上海久合机电工程成套公司 | B31: 1000004358 | C31: CN | D31: 上海久合机电工程成套公司 | E31: 上海市 | F31: 上海市 | G31: 106623 | H31: 上海水电路300号（金鸿苑）12幢2单元101室 | I31: Z001 | J31: ZH | K31: 13701988075 | L31: 310115132319275 | N31: 9776 | O31: 42735 | P31: FI01 | S31: 公司
A32: 上海聚怡清洗服务有限公司 | B32: 2000001635 | C32: CN | D32: 上海聚怡清洗服务有限公司 | E32: 上海市 | F32: 上海市 | G32: 106624 | H32: 上海市嘉定区菊园新区树屏路588弄19号2022室 | I32: Z002 | J32: ZH | K32: 18932152521 | L32: 91310114078189958W | N32: 9776 | O32: 42735 | P32: FI01 | S32: 公司
A33: 上海克灵思容一环境工程事务所 | B33: 2000001636 | C33: CN | D33: 上海克灵思容一环境工程事务所 | E33: 上海市 | F33: 上海市 | G33: 106625 | H33: 上海市长宁区789号1号楼1104室 | I33: Z002 | J33: ZH | K33: 13916147910 | L33: 91310118560149348R | N33: 9776 | O33: 42735 | P33: FI01 | S33: 公司
A34: 上海霖实清洗服务有限公司 | B34: 4000002944 | C34: CN | D34: 上海霖实清洗服务有限公司 | E34: 上海 | F34: 上海 | G34: 106660 | H34: 上海 | I34: Z004 | J34: ZH | L34: 999 | N34: 9776 | O34: 42735 | P34: FI01 | S34: 公司
A35: 上海霖实清洗服务有限公司计数 | B35: 2000001637 | C35: CN | D35: 上海霖实清洗服务有限公司计数 | E35: 上海市 | F35: 上海市 | G35: 106626 | H35: 上海市徐汇区田林路89弄35号1106室 | I35: Z002 | J35: ZH | K35: 021-64515160 | L35: 91310120745639220U | N35: 9776 | O35: 42735 | P35: FI01 | S35: 公司
A36: 上海普环实业有限公司第三分公司 | B36: 2000001638 | C36: CN | D36: 上海普环实业有限公司第三分公司 | E36: 上海市 | F36: 上海市 | G36: 106627 | H36: 上海市丹巴路1720号 | I36: Z002 | J36: ZH | K36: 13764955501 | L36: 913101077683748439 | N36: 9776 | O36: 42735 | P36: FI01 | S36: 公司
A37: 上海燃气（集团）有限公司 | B37: 2000001639 | C37: CN | D37: 上海燃气（集团）有限公司 | F37: 上海市 | G37: 106628 | H37: 上海市安远路706号 | I37: Z002 | J37: ZH | K37: 021-962777 | L37: 999 | N37: 9776 | O37: 42735 | P37: FI01 | S37: 公司
A38: 上海赛奕实业有限公司 | B38: 1000004359 | C38: CN | D38: 上海赛奕实业有限公司 | E38: 上海市 | F38: 上海市 | G38: 106629 | H38: 上海市九星路16号二楼A30 | I38: Z001 | J38: ZH | K38: 15901659941 | L38: 9131011655000847XU | N38: 9776 | O38: 42735 | P38: FI01 | S38: 公司
A39: 上海申煤燃气工程有限公司 | B39: 1000004360 | C39: CN | D39: 上海申煤燃气工程有限公司 | F39: 上海市 | G39: 106630 | H39: 上海市黄浦区制造局路437号181室 | I39: Z001 | J39: ZH | K39: 15239852175 | L39: 91310101744200064P | N39: 9776 | O39: 42735 | P39: FI01 | S39: 公司
A40: 上海饰国建筑工程有限公司 | B40: 1000004375 | C40: CN | D40: 上海饰国建筑工程有限公司 | F40: 上海市 | G40: 106656 | H40: 上海市崇明县长兴镇潘园公路1800号2号楼5071室（上海泰和经济发展 | I40: Z001 | J40: ZH | K40: 13601649703 | L40: 999 | N40: 9776 | O40: 42735 | P40: FI01 | S40: 公司
A41: 上海双舜机电设备安装工程有限公司 | B41: 1000004361 | C41: CN | D41: 上海双舜机电设备安装工程有限公司 | E41: 上海市 | F41: 上海市 | G41: 106631 | H41: 上海市长兴镇海舸路521号 | I41: Z001 | J41: ZH | K41: 15721140368 | L41: 31023000DK00192 | N41: 9776 | O41: 42735 | P41: FI01 | S41: 公司
A42: 上海顺堂室内装饰工程有限公司 | B42: 1000004362 | C42: CN | D42: 上海顺堂室内装饰工程有限公司 | F42: 上海市 | G42: 106632 | H42: 上海市嘉定区兴贤路1378号6幢3281室 | I42: Z001 | J42: ZH | K42: 18915425536 | L42: 9131011456477102XK | N42: 9776 | O42: 42735 | P42: FI01 | S42: 公司
A43: 上海思禾环境技术有限公司 | B43: 1000004363 | C43: CN | D43: 上海思禾环境技术有限公司 | E43: 上海市 | F43: 上海市 | G43: 106633 | H43: 上海市普陀区常和路309号1号楼 | I43: Z001 | J43: ZH | K43: 15601683255 | L43: 999 | N43: 9776 | O43: 42735 | P43: FI01 | S43: 公司
A44: 上海腾隆变配电设备管理有限公司 | B44: 1000004364 | C44: CN | D44: 上海腾隆变配电设备管理有限公司 | E44: 上海市 | F44: 上海市 | G44: 106634 | H44: 上海市宝山区沪太路3100号A座501室 | I44: Z001 | J44: ZH | K44: 13801791428 | L44: 913101067354323653 | N44: 9776 | O44: 42735 | P44: FI01 | S44: 公司
A45: 上海天焰燃气管道工程技术有限公司 | B45: 1000004376 | C45: CN | D45: 上海天焰燃气管道工程技术有限公司 | F45: 上海市 | G45: 106657 | H45: 上海市松江区泖港镇中厍路181号274室 | I45: Z001 | J45: ZH | K45: 13122211286 | L45: 9131011756015872XH | N45: 9776 | O45: 42735 | P45: FI01 | S45: 公司
A46: 上海天焰燃气管道工程有限公司 | B46: 4000002945 | C46: CN | D46: 上海天焰燃气管道工程有限公司 | E46: 上海 | F46: 上海 | G46: 106661 | H46: 上海 | I46: Z004 | J46: ZH | L46: 999 | N46: 9776 | O46: 42735 | P46: FI01 | S46: 公司
A47: 上海同演建筑科技有限公司 | B47: 1000004365 | C47: CN | D47: 上海同演建筑科技有限公司 | E47: 上海市 | F47: 上海市 | G47: 106635 | H47: 上海市虹口区四平路778号1202室 | I47: Z001 | J47: ZH | K47: 021-80103700 | L47: 913101097878694978 | N47: 9776 | O47: 42735 | P47: FI01 | S47: 公司
A48: 上海统一星巴克咖啡有限公司 | B48: 2000001640 | C48: CN | D48: 上海统一星巴克咖啡有限公司 | E48: 上海市 | F48: 上海市 | G48: 106636 | H48: 上海市淮海中路937号金叶大楼第一、二层 | I48: Z002 | J48: ZH | K48: 4000092655 | L48: 913100006074138050 | N48: 9776 | O48: 42735 | P48: FI01 | S48: 公司
A49: 上海兴盛消防集团有限公司 | B49: 1000004366 | C49: CN | D49: 上海兴盛消防集团有限公司 | E49: 上海市 | F49: 上海市 | G49: 106637 | H49: 上海市宝山区共和新路5000弄6号楼17楼 | I49: Z001 | J49: ZH | K49: 13611945358 | L49: 91310000133413095G | N49: 9776 | O49: 42735 | P49: FI01 | S49: 公司
A50: 上海序木工艺品有限公司 | B50: 1000004367 | C50: CN | D50: 上海序木工艺品有限公司 | F50: 上海市 | G50: 106638 | H50: 上海市普陀区长寿路1118号2层L2-16室 | I50: Z001 | J50: ZH | K50: 021-80103700 | L50: 999 | N50: 9776 | O50: 42735 | P50: FI01 | S50: 公司
A51: 上海宜之普图文设计有限公司 | B51: 4000002946 | C51: CN | D51: 上海宜之普图文设计有限公司 | E51: 上海 | F51: 上海 | G51: 106662 | H51: 上海 | I51: Z004 | J51: ZH | L51: 999 | N51: 9776 | O51: 42735 | P51: FI01 | S51: 公司
A52: 上海永途装饰工程有限公司 | B52: 1000004368 | C52: CN | D52: 上海永途装饰工程有限公司 | E52: 上海市 | F52: 上海市 | G52: 106639 | H52: 上海嘉定区安亭镇墨玉路185号 | I52: Z001 | J52: ZH | K52: 13901890983 | L52: 999 | N52: 9776 | O52: 42735 | P52: FI01 | S52: 公司
A53: 上海源安安全科技有限公司 | B53: 1000004369 | C53: CN | D53: 上海源安安全科技有限公司 | E53: 上海市 | F53: 上海市 | G53: 106640 | H53: 上海市宝山区菊联路589弄292号 | I53: Z001 | J53: ZH | K53: 13524606373 | L53: 999 | N53: 9776 | O53: 42735 | P53: FI01 | S53: 公司
A54: 上海中向瑞辰汽车清洁服务有限公司 | B54: 1000004370 | C54: CN | D54: 上海中向瑞辰汽车清洁服务有限公司 | E54: 上海市 | F54: 上海市 | G54: 106641 | H54: 上海市普陀区真北路3562号1楼F1010室 | I54: Z001 | J54: ZH | K54: 021-52650122 | L54: 91310107583483357U | N54: 9776 | O54: 42735 | P54: FI01 | S54: 公司
A55: 苏州科达液压电梯有限公司上海销售分公司 | B55: 1000004371 | C55: CN | D55: 苏州科达液压电梯有限公司上海销售分公司 | E55: 上海市 | F55: 上海市 | G55: 106642 | H55: 上海市长宁区仙霞路888弄104号201室 | I55: Z001 | J55: ZH | K55: 021-62339681 | L55: 913101057647058442 | N55: 9776 | O55: 42735 | P55: FI01 | S55: 公司
A56: 索博客科技（深圳）有限公司 | B56: 4000002947 | C56: CN | D56: 索博客科技（深圳）有限公司 | E56: 深圳 | F56: 深圳 | G56: 106663 | H56: 深圳 | I56: Z004 | J56: ZH | L56: 999 | N56: 9776 | O56: 42735 | P56: FI01 | S56: 公司
A57: 同昌盛业(北京)资产管理顾问有限公司 | B57: 2000001641 | C57: CN | D57: 同昌盛业(北京)资产管理顾问有限公司 | E57: 北京市 | F57: 北京市 | G57: 106643 | H57: 北京市朝阳区望京东园一区120号楼2层至6层101内5层 | I57: Z002 | J57: ZH | K57: 010-59942255 | L57: 110101553134236 | N57: 9776 | O57: 42735 | P57: FI01 | S57: 公司
A58: 同昌盛业（北京）资产管理顾问有限公司 | B58: 4000002948 | C58: CN | D58: 同昌盛业（北京）资产管理顾问有限公司 | E58: 北京 | F58: 北京 | G58: 106664 | H58: 北京 | I58: Z004 | J58: ZH | L58: 999 | N58: 9776 | O58: 42735 | P58: FI01 | S58: 公司
A59: 王蔚茜 | B59: 2000001642 | C59: CN | D59: 王蔚茜 | F59: 上海市 | G59: 106644 | H59: 上海市虹口区花园路 | I59: Z002 | J59: ZH | K59: 13615856582 | L59: 999 | N59: 9776 | O59: 42735 | P59: FI01 | S59: 女士
A60: 威华停车场管理（上海）有限公司 | B60: 2000001643 | C60: CN | D60: 威华停车场管理（上海）有限公司 | E60: 上海市 | F60: 上海市 | G60: 106645 | H60: 上海市徐汇区天钥桥路333号腾飞大厦1603室 | I60: Z002 | J60: ZH | K60: 021-33680156 | L60: 310115666014150 | N60: 9776 | O60: 42735 | P60: FI01 | S60: 公司
A61: 西子奥的斯电梯有限公司上海分公司 | B61: 1000004372 | C61: CN | D61: 西子奥的斯电梯有限公司上海分公司 | E61: 上海市 | F61: 上海市 | G61: 106646 | H61: 上海市徐汇区龙漕路299号（天华信息科技园）2C座10楼 | I61: Z001 | J61: ZH | K61: 18516115675 | L61: 91310000X0726958XK | N61: 9776 | O61: 42735 | P61: FI01 | S61: 公司
A62: 永丰余投资有限公司 | B62: 2000001644 | C62: CN | D62: 永丰余投资有限公司 | E62: 上海市 | F62: 上海市 | G62: 106647 | H62: 上海市静安区共和新路4718弄6号楼（宏慧新汇园）3楼 | I62: Z002 | J62: ZH | K62: 13901945006 | L62: 913100007178838087 | N62: 9776 | O62: 42735 | P62: FI01 | S62: 公司
A63: 张笑 | B63: 2000001645 | C63: CN | D63: 张笑 | F63: 上海市 | G63: 106648 | H63: 上海市普陀区兰溪路 | I63: Z002 | J63: ZH | K63: 13832562314 | L63: 999 | N63: 9776 | O63: 42735 | P63: FI01 | S63: 女士
A64: 长风社区公益卫生保洁服务社 | B64: 2000001646 | C64: CN | D64: 长风社区公益卫生保洁服务社 | E64: 上海市 | F64: 上海市 | G64: 106649 | H64: 上海市普陀区怒江路472号 | I64: Z002 | J64: ZH | K64: 021-62609513 | L64: 999 | N64: 9776 | O64: 42735 | P64: FI01 | S64: 公司
A65: 中国银行股份有限公司 | B65: 2000001647 | C65: CN | D65: 中国银行股份有限公司 | E65: 上海市 | F65: 上海市 | G65: 106650 | H65: 上海市南京西路1215号 | I65: Z002 | J65: ZH | K65: 021-95566 | L65: 999 | N65: 9776 | O65: 42735 | P65: FI01 | S65: 公司
A66: 朱丹贲 | B66: 2000001648 | C66: CN | D66: 朱丹贲 | F66: 上海市 | G66: 106651 | H66: 上海普陀区光复西路 | I66: Z002 | J66: ZH | K66: 13601512447 | L66: 999 | N66: 9776 | O66: 42735 | P66: FI01 | S66: 女士
A67: 朱杰 | B67: 2000001649 | C67: CN | D67: 朱杰 | F67: 上海市 | G67: 106652 | H67: 上海市嘉定区马陆浏翔公路 | I67: Z002 | J67: ZH | K67: 18110695216 | L67: 999 | N67: 9776 | O67: 42735 | P67: FI01 | S67: 先生
A68: 国网上海市电力公司 | B68: 1000001541 | C68: CN | D68: 国网上海市电力公司 | E68: 南京东路181号 | G68: 48135 | I68: Z001 | J68: ZH | L68: 999 | N68: 9776 | O68: 42735 | P68: FI01 | S68: 公司
A69: 上海城投水务（集团）有限公司 | B69: 1000001315 | C69: CN | D69: 上海城投水务（集团）有限公司 | E69: 上海市杨浦区杨树浦路830号76幢 | G69: 47909 | I69: Z001 | J69: ZH | L69: 999 | N69: 9776 | O69: 42735 | P69: FI01 | S69: 公司
A70: 未区分供应商 | B70: 4000000660 | C70: CN | D70: 未区分供应商 | G70: 46899 | I70: Z004 | J70: ZH | L70: 999 | N70: 9776 | O70: 42739 | P70: FI01 | S70: 公司
A71: 上海和企文化传播有限公司 | B71: 4000003054 | C71: CN | D71: 上海和企文化传播有限公司 | E71: 上海市 | F71: 上海市 | G71: 107128 | H71: 上海市 | I71: Z004 | J71: ZH | L71: 999 | N71: 9776 | O71: 42739 | P71: FI01 | S71: 公司
A72: 上海科传信息技术有限公司 | B72: 4000003055 | C72: CN | D72: 上海科传信息技术有限公司 | E72: 上海市 | F72: 上海市 | G72: 107129 | H72: 上海市 | I72: Z004 | J72: ZH | L72: 999 | N72: 9776 | O72: 42739 | P72: FI01 | S72: 公司
A73: 上海圣泰保安服务有限公司 | B73: 4000003056 | C73: CN | D73: 上海圣泰保安服务有限公司 | E73: 上海市 | F73: 上海市 | G73: 107130 | H73: 上海市 | I73: Z004 | J73: ZH | L73: 999 | N73: 9776 | O73: 42739 | P73: FI01 | S73: 公司
A74: 上海知轩 | B74: 4000003057 | C74: CN | D74: 上海知轩 | E74: 上海市 | F74: 上海市 | G74: 107131 | H74: 上海市 | I74: Z004 | J74: ZH | L74: 999 | N74: 9776 | O74: 42739 | P74: FI01 | S74: 公司
A75: 上海市普陀区国家税务局 | B75: 4000003058 | C75: CN | D75: 上海市普陀区国家税务局 | E75: 上海市 | F75: 上海市 | G75: 107132 | H75: 上海市 | I75: Z004 | J75: ZH | L75: 999 | N75: 9776 | O75: 42739 | P75: FI01 | S75: 公司
A76: 百达饮用水 | B76: 4000003059 | C76: CN | D76: 百达饮用水 | E76: 上海市 | F76: 上海市 | G76: 107133 | H76: 上海市 | I76: Z004 | J76: ZH | L76: 999 | N76: 9776 | O76: 42739 | P76: FI01 | S76: 公司
A77: 轩苏办公（太邱设备） | B77: 4000003060 | C77: CN | D77: 轩苏办公（太邱设备） | E77: 上海市 | F77: 上海市 | G77: 107134 | H77: 上海市 | I77: Z004 | J77: ZH | L77: 999 | N77: 9776 | O77: 42739 | P77: FI01 | S77: 公司
A78: 网购 | B78: 4000003061 | C78: CN | D78: 网购 | E78: 上海市 | F78: 上海市 | G78: 107135 | H78: 上海市 | I78: Z004 | J78: ZH | L78: 999 | N78: 9776 | O78: 42739 | P78: FI01 | S78: 公司
A79: 平峰科技 | B79: 4000003062 | C79: CN | D79: 平峰科技 | E79: 上海市 | F79: 上海市 | G79: 107136 | H79: 上海市 | I79: Z004 | J79: ZH | L79: 999 | N79: 9776 | O79: 42739 | P79: FI01 | S79: 公司
A80: 志英广告 | B80: 4000003063 | C80: CN | D80: 志英广告 | E80: 上海市 | F80: 上海市 | G80: 107137 | H80: 上海市 | I80: Z004 | J80: ZH | L80: 999 | N80: 9776 | O80: 42739 | P80: FI01 | S80: 公司
A81: 中国联合网络通信有限公司上海市分公司 | B81: 2000001662 | C81: CN | D81: 中国联合网络通信有限公司上海市分公司 | E81: 上海市 | F81: 上海市 | G81: 107548 | H81: 上海市浦东新区严桥路410号 | I81: Z002 | J81: ZH | K81: 021-80103700 | L81: 999 | N81: 9776 | O81: 42744 | P81: FI01 | S81: 公司
A82: 上海市地方税务局普陀分局 | B82: 2000001663 | C82: CN | D82: 上海市地方税务局普陀分局 | E82: 上海市 | F82: 上海市 | G82: 107549 | H82: 北石路579号 | I82: Z002 | J82: ZH | K82: 021-52564588 | L82: 999 | N82: 9776 | O82: 42744 | P82: FI01 | S82: 公司
A83: 上海文之选商务有限公司 | B83: 2000001664 | C83: CN | D83: 上海文之选商务有限公司 | E83: 上海市 | F83: 上海市 | G83: 107550 | H83: 上海市徐汇区中山南二路481号43号楼3楼北 | I83: Z002 | J83: ZH | K83: 021-80103700 | L83: 91310104729368598L | N83: 9776 | O83: 42744 | P83: FI01 | S83: 公司
A84: 北京大成（上海）律师事务所 | B84: 2000001665 | C84: CN | D84: 北京大成（上海）律师事务所 | E84: 北京市 | F84: 北京市 | G84: 107551 | H84: 上海市浦东新区浦东南路500号国家开发银行大厦3层/30层 | I84: Z002 | J84: ZH | K84: 021-80103700 | L84: 999 | N84: 9776 | O84: 42744 | P84: FI01 | S84: 公司
A85: 工程投标 | B85: 2000001666 | C85: CN | D85: 工程投标 | E85: 上海市 | F85: 上海市 | G85: 107552 | H85: 上海市普陀区大渡河路196号 | I85: Z002 | J85: ZH | K85: 021-80103700 | L85: 999 | N85: 9776 | O85: 42744 | P85: FI01 | S85: 公司
A86: 上海众宁消防安全技术有限公司 | B86: 2000001667 | C86: CN | D86: 上海众宁消防安全技术有限公司 | E86: 上海市 | F86: 上海市 | G86: 107553 | H86: 上海崇明永冠经济开发区（向化公路1556号） | I86: Z002 | J86: ZH | K86: 021-80103700 | L86: 999 | N86: 9776 | O86: 42744 | P86: FI01 | S86: 公司
A87: 北京市中伦（上海）律师事务公司 | B87: 2000001668 | C87: CN | D87: 北京市中伦（上海）律师事务公司 | E87: 上海市 | F87: 上海市 | G87: 107554 | H87: 世纪大道8号国金中心二期10-11层 | I87: Z002 | J87: ZH | K87: 021-80103700 | L87: 999 | N87: 9776 | O87: 42744 | P87: FI01 | S87: 公司
A88: 天职国际会计师事务所 | B88: 2000001669 | C88: CN | D88: 天职国际会计师事务所 | E88: 上海市 | F88: 上海市 | G88: 107555 | H88: 上海市浦东新区丰和路1号港务大厦南楼21层.北楼14层 | I88: Z002 | J88: ZH | K88: 021-51028018 | L88: 999 | N88: 9776 | O88: 42744 | P88: FI01 | S88: 公司
A89: 研策部 | B89: 2000001670 | C89: CN | D89: 研策部 | E89: 上海市 | F89: 上海市 | G89: 107556 | H89: 上海市普陀区大渡河路196号 | I89: Z002 | J89: ZH | K89: 021-80103700 | L89: 999 | N89: 9776 | O89: 42744 | P89: FI01 | S89: 公司
A90: 运营部 | B90: 2000001671 | C90: CN | D90: 运营部 | E90: 上海市 | F90: 上海市 | G90: 107557 | H90: 上海市普陀区大渡河路196号 | I90: Z002 | J90: ZH | K90: 021-80103700 | L90: 999 | N90: 9776 | O90: 42744 | P90: FI01 | S90: 公司
A91: 推广部 | B91: 2000001672 | C91: CN | D91: 推广部 | E91: 上海市 | F91: 上海市 | G91: 107558 | H91: 上海市普陀区大渡河路196号 | I91: Z002 | J91: ZH | K91: 021-80103700 | L91: 999 | N91: 9776 | O91: 42744 | P91: FI01 | S91: 公司
A92: 物业部 | B92: 2000001673 | C92: CN | D92: 物业部 | E92: 上海市 | F92: 上海市 | G92: 107559 | H92: 上海市普陀区大渡河路196号 | I92: Z002 | J92: ZH | K92: 021-80103700 | L92: 999 | N92: 9776 | O92: 42744 | P92: FI01 | S92: 公司
A93: 其他 | B93: 4000000680 | C93: CN | D93: 其他 | G93: 46950 | I93: Z004 | J93: ZH | L93: 999 | N93: 9776 | O93: 42744 | P93: FI01 | S93: 公司
A94: 上海知轩人力资源有限公司 | B94: 2000001674 | C94: CN | D94: 上海知轩人力资源有限公司 | G94: 107849 | I94: Z002 | J94: ZH | L94: 999 | N94: 9776 | O94: 42744 | P94: FI01 | S94: 公司

Sheet Sheet2
A1: 北京燕侨物业管理有限公司 | B1: =VLOOKUP(A1,Sheet1!$A$2:$B$94,2,FALSE) -> 2000001624
A2: 戴勇 | B2: =VLOOKUP(A2,Sheet1!$A$2:$B$94,2,FALSE) -> 2000001625
A3: 工商银行上海市浦东分行 | B3: =VLOOKUP(A3,Sheet1!$A$2:$B$94,2,FALSE) -> 3000000465
A4: 国网上海市电力公司 | B4: =VLOOKUP(A4,Sheet1!$A$2:$B$94,2,FALSE) -> 1000001541
A5: 金叶俊 | B5: =VLOOKUP(A5,Sheet1!$A$2:$B$94,2,FALSE) -> 2000001627
A6: 润森环境服务（上海）有限公司 | B6: =VLOOKUP(A6,Sheet1!$A$2:$B$94,2,FALSE) -> 2000001628
A7: 上海安保设备开发工程有限公司 | B7: =VLOOKUP(A7,Sheet1!$A$2:$B$94,2,FALSE) -> 1000004348
A8: 上海博世机电设施工程有限公司 | B8: =VLOOKUP(A8,Sheet1!$A$2:$B$94,2,FALSE) -> 1000004349
A9: 上海不唯间贸易有限公司 | B9: =VLOOKUP(A9,Sheet1!$A$2:$B$94,2,FALSE) -> 2000001629
A10: 上海步景标识有限公司 | B10: =VLOOKUP(A10,Sheet1!$A$2:$B$94,2,FALSE) -> 1000004350
A11: 上海城投水务（集团）有限公司 | B11: =VLOOKUP(A11,Sheet1!$A$2:$B$94,2,FALSE) -> 1000001315
A12: 上海春婕花木园艺有限公司 | B12: =VLOOKUP(A12,Sheet1!$A$2:$B$94,2,FALSE) -> 2000001631
... A82: 其他 | B82: =VLOOKUP(A82,Sheet1!$A$2:$B$94,2,FALSE) -> 4000000680
